{"cache":[["keyv:spotify-top_length",{"value":"{\"value\":5,\"expires\":null}"}],["keyv:spotify-top_index",{"value":"{\"value\":4,\"expires\":null}"}],["keyv:spotify-top_0",{"value":"{\"value\":\"https://open.spotify.com/track/4R9W8aH6fHTc8VaUgu72Ol\",\"expires\":null}"}],["keyv:spotify-top_1",{"value":"{\"value\":\"https://open.spotify.com/track/4ZvC18esIKLSUgYCf8YJjK\",\"expires\":null}"}],["keyv:spotify-top_2",{"value":"{\"value\":\"https://open.spotify.com/track/4AORw3gqmbgPt2X1bCtynl\",\"expires\":null}"}],["keyv:spotify-top_3",{"value":"{\"value\":\"https://open.spotify.com/track/797Vk2YjznpSZfslJURmaS\",\"expires\":null}"}],["keyv:spotify-top_4",{"value":"{\"value\":\"https://open.spotify.com/track/2CfUCjGG1dlJxhkreYvZV8\",\"expires\":null}"}],["keyv:counter",{"value":"{\"value\":0,\"expires\":null}"}]],"lastExpire":1632028273546}